[
    {
        "time_map": {
            "[[[[DT_0]]]]": [
                -1, 
                81549, 
                7151
            ], 
            "[[[[DT_10]]]]": [
                0, 
                2, 
                7151
            ], 
            "[[[[DT_11]]]]": [
                0, 
                2, 
                904885
            ], 
            "[[[[DT_12]]]]": [
                0, 
                3, 
                9912
            ], 
            "[[[[DT_13]]]]": [
                0, 
                3, 
                7151
            ], 
            "[[[[DT_14]]]]": [
                0, 
                3, 
                219525
            ], 
            "[[[[DT_15]]]]": [
                0, 
                3, 
                397263
            ], 
            "[[[[DT_16]]]]": [
                0, 
                3, 
                425183
            ], 
            "[[[[DT_17]]]]": [
                0, 
                3, 
                821166
            ], 
            "[[[[DT_18]]]]": [
                0, 
                14, 
                7151
            ], 
            "[[[[DT_19]]]]": [
                0, 
                14, 
                730590
            ], 
            "[[[[DT_1]]]]": [
                -1, 
                85917, 
                7151
            ], 
            "[[[[DT_20]]]]": [
                0, 
                14, 
                871727
            ], 
            "[[[[DT_21]]]]": [
                0, 
                15, 
                7151
            ], 
            "[[[[DT_22]]]]": [
                0, 
                15, 
                161036
            ], 
            "[[[[DT_23]]]]": [
                0, 
                18, 
                7151
            ], 
            "[[[[DT_24]]]]": [
                0, 
                18, 
                74007
            ], 
            "[[[[DT_25]]]]": [
                0, 
                18, 
                249741
            ], 
            "[[[[DT_26]]]]": [
                0, 
                18, 
                460592
            ], 
            "[[[[DT_27]]]]": [
                0, 
                23, 
                7151
            ], 
            "[[[[DT_28]]]]": [
                0, 
                23, 
                795448
            ], 
            "[[[[DT_29]]]]": [
                0, 
                28, 
                7151
            ], 
            "[[[[DT_2]]]]": [
                -1, 
                85985, 
                7151
            ], 
            "[[[[DT_30]]]]": [
                0, 
                28, 
                815002
            ], 
            "[[[[DT_31]]]]": [
                0, 
                29, 
                7151
            ], 
            "[[[[DT_32]]]]": [
                0, 
                29, 
                306157
            ], 
            "[[[[DT_33]]]]": [
                0, 
                38, 
                7151
            ], 
            "[[[[DT_34]]]]": [
                0, 
                38, 
                180531
            ], 
            "[[[[DT_35]]]]": [
                0, 
                3669, 
                7151
            ], 
            "[[[[DT_36]]]]": [
                0, 
                3669, 
                300453
            ], 
            "[[[[DT_37]]]]": [
                0, 
                3669, 
                562942
            ], 
            "[[[[DT_38]]]]": [
                0, 
                3669, 
                996225
            ], 
            "[[[[DT_39]]]]": [
                0, 
                3670, 
                23417
            ], 
            "[[[[DT_3]]]]": [
                -1, 
                86399, 
                7151
            ], 
            "[[[[DT_4]]]]": [
                0, 
                0, 
                0
            ], 
            "[[[[DT_5]]]]": [
                -1, 
                86396, 
                80202
            ], 
            "[[[[DT_6]]]]": [
                0, 
                0, 
                7151
            ], 
            "[[[[DT_7]]]]": [
                0, 
                0, 
                88591
            ], 
            "[[[[DT_8]]]]": [
                0, 
                1, 
                7151
            ], 
            "[[[[DT_9]]]]": [
                0, 
                2, 
                60511
            ]
        }, 
        "uuid": 28, 
        "v4": 6, 
        "v6": 1, 
        "xuuid": 24
    }, 
    {
        "_context_auth_token": "[[[[XUUID_0]]]]", 
        "_context_glance_api_servers": null, 
        "_context_instance_lock_checked": false, 
        "_context_is_admin": false, 
        "_context_project_id": "[[[[tenant_id]]]]", 
        "_context_project_name": "[[[[tenant_id]]]]", 
        "_context_quota_class": null, 
        "_context_read_deleted": "no", 
        "_context_remote_address": "[[[[V4_2]]]]", 
        "_context_request_id": "req-[[[[UUID_0]]]]", 
        "_context_roles": [
            "checkmate", 
            "object-store:default", 
            "compute:default", 
            "identity:user-admin"
        ], 
        "_context_tenant": "[[[[tenant_id]]]]", 
        "_context_timestamp": "[[[[DT_5]]]]", 
        "_context_user": "[[[[user_id]]]]", 
        "_context_user_id": "[[[[user_id]]]]", 
        "_context_user_name": "[[[[user_id]]]]", 
        "_unique_id": "[[[[XUUID_1]]]]", 
        "event_type": "compute.instance.update", 
        "message_id": "[[[[UUID_4]]]]", 
        "payload": {
            "access_ip_v4": "[[[[V4_0]]]]", 
            "access_ip_v6": "[[[[V6_0]]]]", 
            "architecture": "x64", 
            "audit_period_beginning": "[[[[DT_0]]]]", 
            "audit_period_ending": "[[[[DT_3]]]]", 
            "availability_zone": null, 
            "bandwidth": {}, 
            "created_at": "[[[[DT_1]]]]", 
            "deleted_at": "", 
            "disk_gb": 40, 
            "display_name": "[[[[display_name]]]]", 
            "ephemeral_gb": 0, 
            "host": "[[[[host]]]]", 
            "hostname": "[[[[hostname]]]]", 
            "image_meta": {
                "auto_disk_config": "disabled", 
                "base_image_ref": "[[[[UUID_3]]]]", 
                "cache_in_nova": "True", 
                "container_format": "ovf", 
                "disk_format": "vhd", 
                "image_type": "base", 
                "min_disk": "40", 
                "min_ram": "512", 
                "org.openstack__1__architecture": "x64", 
                "org.openstack__1__os_distro": "org.debian", 
                "org.openstack__1__os_version": "7", 
                "os_distro": "debian", 
                "os_type": "linux", 
                "vm_mode": "hvm"
            }, 
            "image_ref_url": "http://[[[[V4_1]]]]:9292/images/[[[[UUID_2]]]]", 
            "instance_flavor_id": "3", 
            "instance_id": "[[[[UUID_1]]]]", 
            "instance_type": "1GB Standard Instance", 
            "instance_type_id": 3, 
            "kernel_id": "", 
            "launched_at": "[[[[DT_2]]]]", 
            "memory_mb": 1024, 
            "metadata": {}, 
            "new_task_state": "rebuilding", 
            "node": "[[[[node]]]]", 
            "old_state": "active", 
            "old_task_state": null, 
            "os_type": "linux", 
            "ramdisk_id": "", 
            "reservation_id": "[[[[reservation_id]]]]", 
            "root_gb": 40, 
            "state": "active", 
            "state_description": "rebuilding", 
            "tenant_id": "[[[[tenant_id]]]]", 
            "terminated_at": "", 
            "user_id": "[[[[user_id]]]]", 
            "vcpus": 1
        }, 
        "priority": "INFO", 
        "publisher_id": "[[[[publisher_id]]]]", 
        "timestamp": "[[[[DT_4]]]]"
    }, 
    {
        "_context_auth_token": "[[[[XUUID_0]]]]", 
        "_context_glance_api_servers": null, 
        "_context_instance_lock_checked": false, 
        "_context_is_admin": false, 
        "_context_project_id": "[[[[tenant_id]]]]", 
        "_context_project_name": "[[[[tenant_id]]]]", 
        "_context_quota_class": null, 
        "_context_read_deleted": "no", 
        "_context_remote_address": "[[[[V4_2]]]]", 
        "_context_request_id": "req-[[[[UUID_0]]]]", 
        "_context_roles": [
            "checkmate", 
            "object-store:default", 
            "compute:default", 
            "identity:user-admin"
        ], 
        "_context_tenant": "[[[[tenant_id]]]]", 
        "_context_timestamp": "[[[[DT_5]]]]", 
        "_context_user": "[[[[user_id]]]]", 
        "_context_user_id": "[[[[user_id]]]]", 
        "_context_user_name": "[[[[user_id]]]]", 
        "_unique_id": "[[[[XUUID_2]]]]", 
        "event_type": "compute.instance.update", 
        "message_id": "[[[[UUID_5]]]]", 
        "payload": {
            "access_ip_v4": "[[[[V4_0]]]]", 
            "access_ip_v6": "[[[[V6_0]]]]", 
            "architecture": "x64", 
            "audit_period_beginning": "[[[[DT_0]]]]", 
            "audit_period_ending": "[[[[DT_6]]]]", 
            "availability_zone": null, 
            "bandwidth": {
                "private": {
                    "bw_in": 0, 
                    "bw_out": 0
                }, 
                "public": {
                    "bw_in": 0, 
                    "bw_out": 0
                }
            }, 
            "created_at": "[[[[DT_1]]]]", 
            "deleted_at": "", 
            "disk_gb": 40, 
            "display_name": "[[[[display_name]]]]", 
            "ephemeral_gb": 0, 
            "host": "[[[[host]]]]", 
            "hostname": "[[[[hostname]]]]", 
            "image_meta": {
                "auto_disk_config": "disabled", 
                "base_image_ref": "[[[[UUID_3]]]]", 
                "cache_in_nova": "True", 
                "container_format": "ovf", 
                "disk_format": "vhd", 
                "image_type": "base", 
                "min_disk": "40", 
                "min_ram": "512", 
                "org.openstack__1__architecture": "x64", 
                "org.openstack__1__os_distro": "org.debian", 
                "org.openstack__1__os_version": "7", 
                "os_distro": "debian", 
                "os_type": "linux", 
                "vm_mode": "hvm"
            }, 
            "image_ref_url": "http://[[[[V4_3]]]]:9292/images/[[[[UUID_2]]]]", 
            "instance_flavor_id": "3", 
            "instance_id": "[[[[UUID_1]]]]", 
            "instance_type": "1GB Standard Instance", 
            "instance_type_id": 3, 
            "kernel_id": "", 
            "launched_at": "[[[[DT_2]]]]", 
            "memory_mb": 1024, 
            "metadata": {}, 
            "new_task_state": null, 
            "node": "[[[[node]]]]", 
            "old_display_name": "LON-Managed-Linux-Server581099447514", 
            "old_state": null, 
            "old_task_state": null, 
            "os_type": "linux", 
            "ramdisk_id": "", 
            "reservation_id": "[[[[reservation_id]]]]", 
            "root_gb": 40, 
            "state": "active", 
            "state_description": "", 
            "tenant_id": "[[[[tenant_id]]]]", 
            "terminated_at": "", 
            "user_id": "[[[[user_id]]]]", 
            "vcpus": 1
        }, 
        "priority": "INFO", 
        "publisher_id": "[[[[publisher_id]]]]", 
        "timestamp": "[[[[DT_7]]]]"
    }, 
    {
        "_context_auth_token": "[[[[XUUID_0]]]]", 
        "_context_glance_api_servers": null, 
        "_context_instance_lock_checked": false, 
        "_context_is_admin": false, 
        "_context_project_id": "[[[[tenant_id]]]]", 
        "_context_project_name": "[[[[tenant_id]]]]", 
        "_context_quota_class": null, 
        "_context_read_deleted": "no", 
        "_context_remote_address": "[[[[V4_2]]]]", 
        "_context_request_id": "req-[[[[UUID_0]]]]", 
        "_context_roles": [
            "checkmate", 
            "object-store:default", 
            "compute:default", 
            "identity:user-admin"
        ], 
        "_context_tenant": "[[[[tenant_id]]]]", 
        "_context_timestamp": "[[[[DT_5]]]]", 
        "_context_user": "[[[[user_id]]]]", 
        "_context_user_id": "[[[[user_id]]]]", 
        "_context_user_name": "[[[[user_id]]]]", 
        "_unique_id": "[[[[XUUID_3]]]]", 
        "event_type": "compute.instance.update", 
        "message_id": "[[[[UUID_6]]]]", 
        "payload": {
            "access_ip_v4": "[[[[V4_0]]]]", 
            "access_ip_v6": "[[[[V6_0]]]]", 
            "architecture": "x64", 
            "audit_period_beginning": "[[[[DT_0]]]]", 
            "audit_period_ending": "[[[[DT_8]]]]", 
            "availability_zone": null, 
            "bandwidth": {}, 
            "created_at": "[[[[DT_1]]]]", 
            "deleted_at": "", 
            "disk_gb": 40, 
            "display_name": "[[[[display_name]]]]", 
            "ephemeral_gb": 0, 
            "host": "[[[[host]]]]", 
            "hostname": "[[[[hostname]]]]", 
            "image_meta": {
                "auto_disk_config": "True", 
                "cache_in_nova": "True", 
                "container_format": "ovf", 
                "disk_format": "vhd", 
                "image_type": "base", 
                "min_disk": 40, 
                "min_ram": 512, 
                "org.openstack__1__architecture": "x64", 
                "org.openstack__1__os_distro": "org.centos", 
                "org.openstack__1__os_version": "5.10", 
                "os_distro": "centos", 
                "os_type": "linux"
            }, 
            "image_ref_url": "http://[[[[V4_1]]]]:9292/images/[[[[UUID_2]]]]", 
            "instance_flavor_id": "3", 
            "instance_id": "[[[[UUID_1]]]]", 
            "instance_type": "1GB Standard Instance", 
            "instance_type_id": 3, 
            "kernel_id": "", 
            "launched_at": "[[[[DT_2]]]]", 
            "memory_mb": 1024, 
            "metadata": {}, 
            "new_task_state": "rebuilding", 
            "node": "[[[[node]]]]", 
            "old_state": null, 
            "old_task_state": null, 
            "os_type": "linux", 
            "ramdisk_id": "", 
            "reservation_id": "[[[[reservation_id]]]]", 
            "root_gb": 40, 
            "state": "active", 
            "state_description": "rebuilding", 
            "tenant_id": "[[[[tenant_id]]]]", 
            "terminated_at": "", 
            "user_id": "[[[[user_id]]]]", 
            "vcpus": 1
        }, 
        "priority": "INFO", 
        "publisher_id": "[[[[publisher_id]]]]", 
        "timestamp": "[[[[DT_9]]]]"
    }, 
    {
        "_context_auth_token": "[[[[XUUID_0]]]]", 
        "_context_glance_api_servers": null, 
        "_context_instance_lock_checked": false, 
        "_context_is_admin": false, 
        "_context_project_id": "[[[[tenant_id]]]]", 
        "_context_project_name": "[[[[tenant_id]]]]", 
        "_context_quota_class": null, 
        "_context_read_deleted": "no", 
        "_context_remote_address": "[[[[V4_2]]]]", 
        "_context_request_id": "req-[[[[UUID_0]]]]", 
        "_context_roles": [
            "checkmate", 
            "object-store:default", 
            "compute:default", 
            "identity:user-admin"
        ], 
        "_context_tenant": "[[[[tenant_id]]]]", 
        "_context_timestamp": "[[[[DT_5]]]]", 
        "_context_user": "[[[[user_id]]]]", 
        "_context_user_id": "[[[[user_id]]]]", 
        "_context_user_name": "[[[[user_id]]]]", 
        "_unique_id": "[[[[XUUID_4]]]]", 
        "event_type": "compute.instance.update", 
        "message_id": "[[[[UUID_7]]]]", 
        "payload": {
            "access_ip_v4": "[[[[V4_0]]]]", 
            "access_ip_v6": "[[[[V6_0]]]]", 
            "architecture": "x64", 
            "audit_period_beginning": "[[[[DT_0]]]]", 
            "audit_period_ending": "[[[[DT_10]]]]", 
            "availability_zone": null, 
            "bandwidth": {
                "private": {
                    "bw_in": 0, 
                    "bw_out": 0
                }, 
                "public": {
                    "bw_in": 0, 
                    "bw_out": 0
                }
            }, 
            "created_at": "[[[[DT_1]]]]", 
            "deleted_at": "", 
            "disk_gb": 40, 
            "display_name": "[[[[display_name]]]]", 
            "ephemeral_gb": 0, 
            "host": "[[[[host]]]]", 
            "hostname": "[[[[hostname]]]]", 
            "image_meta": {
                "auto_disk_config": "disabled", 
                "base_image_ref": "[[[[UUID_3]]]]", 
                "cache_in_nova": "True", 
                "container_format": "ovf", 
                "disk_format": "vhd", 
                "image_type": "base", 
                "min_disk": "40", 
                "min_ram": "512", 
                "org.openstack__1__architecture": "x64", 
                "org.openstack__1__os_distro": "org.debian", 
                "org.openstack__1__os_version": "7", 
                "os_distro": "debian", 
                "os_type": "linux", 
                "vm_mode": "hvm"
            }, 
            "image_ref_url": "http://[[[[V4_3]]]]:9292/images/[[[[UUID_2]]]]", 
            "instance_flavor_id": "3", 
            "instance_id": "[[[[UUID_1]]]]", 
            "instance_type": "1GB Standard Instance", 
            "instance_type_id": 3, 
            "kernel_id": "", 
            "launched_at": "[[[[DT_2]]]]", 
            "memory_mb": 1024, 
            "metadata": {}, 
            "new_task_state": "rebuilding", 
            "node": "[[[[node]]]]", 
            "old_state": "active", 
            "old_task_state": null, 
            "os_type": "linux", 
            "ramdisk_id": "", 
            "reservation_id": "[[[[reservation_id]]]]", 
            "root_gb": 40, 
            "state": "active", 
            "state_description": "rebuilding", 
            "tenant_id": "[[[[tenant_id]]]]", 
            "terminated_at": "", 
            "user_id": "[[[[user_id]]]]", 
            "vcpus": 1
        }, 
        "priority": "INFO", 
        "publisher_id": "[[[[publisher_id]]]]", 
        "timestamp": "[[[[DT_11]]]]"
    }, 
    {
        "_context_auth_token": "[[[[XUUID_0]]]]", 
        "_context_glance_api_servers": null, 
        "_context_instance_lock_checked": false, 
        "_context_is_admin": false, 
        "_context_project_id": "[[[[tenant_id]]]]", 
        "_context_project_name": "[[[[tenant_id]]]]", 
        "_context_quota_class": null, 
        "_context_read_deleted": "no", 
        "_context_remote_address": "[[[[V4_2]]]]", 
        "_context_request_id": "req-[[[[UUID_0]]]]", 
        "_context_roles": [
            "checkmate", 
            "object-store:default", 
            "compute:default", 
            "identity:user-admin"
        ], 
        "_context_tenant": "[[[[tenant_id]]]]", 
        "_context_timestamp": "[[[[DT_5]]]]", 
        "_context_user": "[[[[user_id]]]]", 
        "_context_user_id": "[[[[user_id]]]]", 
        "_context_user_name": "[[[[user_id]]]]", 
        "_unique_id": "[[[[XUUID_5]]]]", 
        "event_type": "compute.instance.update", 
        "message_id": "[[[[UUID_8]]]]", 
        "payload": {
            "access_ip_v4": "[[[[V4_0]]]]", 
            "access_ip_v6": "[[[[V6_0]]]]", 
            "architecture": "x64", 
            "audit_period_beginning": "[[[[DT_0]]]]", 
            "audit_period_ending": "[[[[DT_10]]]]", 
            "availability_zone": null, 
            "bandwidth": {
                "private": {
                    "bw_in": 0, 
                    "bw_out": 0
                }, 
                "public": {
                    "bw_in": 0, 
                    "bw_out": 0
                }
            }, 
            "created_at": "[[[[DT_1]]]]", 
            "deleted_at": "", 
            "disk_gb": 40, 
            "display_name": "[[[[display_name]]]]", 
            "ephemeral_gb": 0, 
            "host": "[[[[host]]]]", 
            "hostname": "[[[[hostname]]]]", 
            "image_meta": {
                "auto_disk_config": "True", 
                "cache_in_nova": "True", 
                "container_format": "ovf", 
                "disk_format": "vhd", 
                "image_type": "base", 
                "min_disk": "40", 
                "min_ram": "512", 
                "org.openstack__1__architecture": "x64", 
                "org.openstack__1__os_distro": "org.centos", 
                "org.openstack__1__os_version": "5.10", 
                "os_distro": "centos", 
                "os_type": "linux"
            }, 
            "image_ref_url": "http://[[[[V4_3]]]]:9292/images/[[[[UUID_2]]]]", 
            "instance_flavor_id": "3", 
            "instance_id": "[[[[UUID_1]]]]", 
            "instance_type": "1GB Standard Instance", 
            "instance_type_id": 3, 
            "kernel_id": "", 
            "launched_at": "[[[[DT_2]]]]", 
            "memory_mb": 1024, 
            "metadata": {}, 
            "new_task_state": "rebuilding", 
            "node": "[[[[node]]]]", 
            "old_state": null, 
            "old_task_state": null, 
            "os_type": "linux", 
            "ramdisk_id": "", 
            "reservation_id": "[[[[reservation_id]]]]", 
            "root_gb": 40, 
            "state": "active", 
            "state_description": "rebuilding", 
            "tenant_id": "[[[[tenant_id]]]]", 
            "terminated_at": "", 
            "user_id": "[[[[user_id]]]]", 
            "vcpus": 1
        }, 
        "priority": "INFO", 
        "publisher_id": "[[[[publisher_id]]]]", 
        "timestamp": "[[[[DT_12]]]]"
    }, 
    {
        "_context_auth_token": "[[[[XUUID_0]]]]", 
        "_context_glance_api_servers": null, 
        "_context_instance_lock_checked": false, 
        "_context_is_admin": false, 
        "_context_project_id": "[[[[tenant_id]]]]", 
        "_context_project_name": "[[[[tenant_id]]]]", 
        "_context_quota_class": null, 
        "_context_read_deleted": "no", 
        "_context_remote_address": "[[[[V4_2]]]]", 
        "_context_request_id": "req-[[[[UUID_0]]]]", 
        "_context_roles": [
            "checkmate", 
            "object-store:default", 
            "compute:default", 
            "identity:user-admin", 
            "admin"
        ], 
        "_context_tenant": "[[[[tenant_id]]]]", 
        "_context_timestamp": "[[[[DT_5]]]]", 
        "_context_user": "[[[[user_id]]]]", 
        "_context_user_id": "[[[[user_id]]]]", 
        "_context_user_name": "[[[[user_id]]]]", 
        "_unique_id": "[[[[XUUID_6]]]]", 
        "event_type": "compute.instance.update", 
        "message_id": "[[[[UUID_9]]]]", 
        "payload": {
            "access_ip_v4": "[[[[V4_0]]]]", 
            "access_ip_v6": "[[[[V6_0]]]]", 
            "architecture": "x64", 
            "audit_period_beginning": "[[[[DT_0]]]]", 
            "audit_period_ending": "[[[[DT_13]]]]", 
            "availability_zone": null, 
            "bandwidth": {
                "private": {
                    "bw_in": 0, 
                    "bw_out": 0
                }, 
                "public": {
                    "bw_in": 0, 
                    "bw_out": 0
                }
            }, 
            "created_at": "[[[[DT_1]]]]", 
            "deleted_at": "", 
            "disk_gb": 40, 
            "display_name": "[[[[display_name]]]]", 
            "ephemeral_gb": 0, 
            "host": "[[[[host]]]]", 
            "hostname": "[[[[hostname]]]]", 
            "image_meta": {
                "auto_disk_config": "True", 
                "cache_in_nova": "True", 
                "container_format": "ovf", 
                "disk_format": "vhd", 
                "image_type": "base", 
                "min_disk": "40", 
                "min_ram": "512", 
                "org.openstack__1__architecture": "x64", 
                "org.openstack__1__os_distro": "org.centos", 
                "org.openstack__1__os_version": "5.10", 
                "os_distro": "centos", 
                "os_type": "linux"
            }, 
            "image_ref_url": "http://[[[[V4_4]]]]:9292/images/[[[[UUID_2]]]]", 
            "instance_flavor_id": "3", 
            "instance_id": "[[[[UUID_1]]]]", 
            "instance_type": "1GB Standard Instance", 
            "instance_type_id": 3, 
            "kernel_id": "", 
            "launched_at": "[[[[DT_13]]]]", 
            "memory_mb": 1024, 
            "metadata": {}, 
            "new_task_state": "rebuilding", 
            "node": "[[[[node]]]]", 
            "old_state": null, 
            "old_task_state": null, 
            "os_type": "linux", 
            "ramdisk_id": "", 
            "reservation_id": "[[[[reservation_id]]]]", 
            "root_gb": 40, 
            "state": "active", 
            "state_description": "rebuilding", 
            "tenant_id": "[[[[tenant_id]]]]", 
            "terminated_at": "", 
            "user_id": "[[[[user_id]]]]", 
            "vcpus": 1
        }, 
        "priority": "INFO", 
        "publisher_id": "[[[[publisher_id]]]]", 
        "timestamp": "[[[[DT_14]]]]"
    }, 
    {
        "_context_auth_token": "[[[[XUUID_0]]]]", 
        "_context_glance_api_servers": null, 
        "_context_instance_lock_checked": false, 
        "_context_is_admin": true, 
        "_context_project_id": "[[[[tenant_id]]]]", 
        "_context_project_name": "[[[[tenant_id]]]]", 
        "_context_quota_class": null, 
        "_context_read_deleted": "no", 
        "_context_remote_address": "[[[[V4_2]]]]", 
        "_context_request_id": "req-[[[[UUID_0]]]]", 
        "_context_roles": [
            "checkmate", 
            "object-store:default", 
            "compute:default", 
            "identity:user-admin", 
            "admin"
        ], 
        "_context_tenant": "[[[[tenant_id]]]]", 
        "_context_timestamp": "[[[[DT_5]]]]", 
        "_context_user": "[[[[user_id]]]]", 
        "_context_user_id": "[[[[user_id]]]]", 
        "_context_user_name": "[[[[user_id]]]]", 
        "_unique_id": "[[[[XUUID_7]]]]", 
        "event_type": "compute.instance.exists.verified", 
        "message_id": "[[[[UUID_10]]]]", 
        "original_message_id": "[[[[UUID_11]]]]", 
        "payload": {
            "access_ip_v4": "[[[[V4_0]]]]", 
            "access_ip_v6": "[[[[V6_0]]]]", 
            "architecture": "x64", 
            "audit_period_beginning": "[[[[DT_0]]]]", 
            "audit_period_ending": "[[[[DT_13]]]]", 
            "availability_zone": null, 
            "bandwidth": {}, 
            "created_at": "[[[[DT_1]]]]", 
            "deleted_at": "", 
            "disk_gb": 40, 
            "display_name": "[[[[display_name]]]]", 
            "ephemeral_gb": 0, 
            "host": "[[[[host]]]]", 
            "hostname": "[[[[hostname]]]]", 
            "image_meta": {
                "auto_disk_config": "disabled", 
                "base_image_ref": "[[[[UUID_3]]]]", 
                "cache_in_nova": "True", 
                "container_format": "ovf", 
                "disk_format": "vhd", 
                "image_type": "base", 
                "min_disk": "40", 
                "min_ram": "512", 
                "org.openstack__1__architecture": "x64", 
                "org.openstack__1__os_distro": "org.debian", 
                "org.openstack__1__os_version": "7", 
                "os_distro": "debian", 
                "os_type": "linux", 
                "vm_mode": "hvm"
            }, 
            "image_ref_url": "http://[[[[V4_4]]]]:9292/images/[[[[UUID_2]]]]", 
            "instance_flavor_id": "3", 
            "instance_id": "[[[[UUID_1]]]]", 
            "instance_type": "1GB Standard Instance", 
            "instance_type_id": 3, 
            "kernel_id": "", 
            "launched_at": "[[[[DT_2]]]]", 
            "memory_mb": 1024, 
            "metadata": {}, 
            "node": "[[[[node]]]]", 
            "os_type": "linux", 
            "ramdisk_id": "", 
            "reservation_id": "[[[[reservation_id]]]]", 
            "root_gb": 40, 
            "state": "active", 
            "state_description": "rebuilding", 
            "tenant_id": "[[[[tenant_id]]]]", 
            "terminated_at": "", 
            "user_id": "[[[[user_id]]]]", 
            "vcpus": 1
        }, 
        "priority": "INFO", 
        "publisher_id": "[[[[publisher_id]]]]", 
        "timestamp": "[[[[DT_15]]]]"
    }, 
    {
        "_context_auth_token": "[[[[XUUID_0]]]]", 
        "_context_glance_api_servers": null, 
        "_context_instance_lock_checked": false, 
        "_context_is_admin": true, 
        "_context_project_id": "[[[[tenant_id]]]]", 
        "_context_project_name": "[[[[tenant_id]]]]", 
        "_context_quota_class": null, 
        "_context_read_deleted": "no", 
        "_context_remote_address": "[[[[V4_2]]]]", 
        "_context_request_id": "req-[[[[UUID_0]]]]", 
        "_context_roles": [
            "checkmate", 
            "object-store:default", 
            "compute:default", 
            "identity:user-admin", 
            "admin"
        ], 
        "_context_tenant": "[[[[tenant_id]]]]", 
        "_context_timestamp": "[[[[DT_5]]]]", 
        "_context_user": "[[[[user_id]]]]", 
        "_context_user_id": "[[[[user_id]]]]", 
        "_context_user_name": "[[[[user_id]]]]", 
        "_unique_id": "[[[[XUUID_7]]]]", 
        "event_type": "compute.instance.exists", 
        "message_id": "[[[[UUID_11]]]]", 
        "payload": {
            "access_ip_v4": "[[[[V4_0]]]]", 
            "access_ip_v6": "[[[[V6_0]]]]", 
            "architecture": "x64", 
            "audit_period_beginning": "[[[[DT_0]]]]", 
            "audit_period_ending": "[[[[DT_13]]]]", 
            "availability_zone": null, 
            "bandwidth": {}, 
            "created_at": "[[[[DT_1]]]]", 
            "deleted_at": "", 
            "disk_gb": 40, 
            "display_name": "[[[[display_name]]]]", 
            "ephemeral_gb": 0, 
            "host": "[[[[host]]]]", 
            "hostname": "[[[[hostname]]]]", 
            "image_meta": {
                "auto_disk_config": "disabled", 
                "base_image_ref": "[[[[UUID_3]]]]", 
                "cache_in_nova": "True", 
                "container_format": "ovf", 
                "disk_format": "vhd", 
                "image_type": "base", 
                "min_disk": "40", 
                "min_ram": "512", 
                "org.openstack__1__architecture": "x64", 
                "org.openstack__1__os_distro": "org.debian", 
                "org.openstack__1__os_version": "7", 
                "os_distro": "debian", 
                "os_type": "linux", 
                "vm_mode": "hvm"
            }, 
            "image_ref_url": "http://[[[[V4_4]]]]:9292/images/[[[[UUID_2]]]]", 
            "instance_flavor_id": "3", 
            "instance_id": "[[[[UUID_1]]]]", 
            "instance_type": "1GB Standard Instance", 
            "instance_type_id": 3, 
            "kernel_id": "", 
            "launched_at": "[[[[DT_2]]]]", 
            "memory_mb": 1024, 
            "metadata": {}, 
            "node": "[[[[node]]]]", 
            "os_type": "linux", 
            "ramdisk_id": "", 
            "reservation_id": "[[[[reservation_id]]]]", 
            "root_gb": 40, 
            "state": "active", 
            "state_description": "rebuilding", 
            "tenant_id": "[[[[tenant_id]]]]", 
            "terminated_at": "", 
            "user_id": "[[[[user_id]]]]", 
            "vcpus": 1
        }, 
        "priority": "INFO", 
        "publisher_id": "[[[[publisher_id]]]]", 
        "timestamp": "[[[[DT_15]]]]"
    }, 
    {
        "_context_auth_token": "[[[[XUUID_0]]]]", 
        "_context_glance_api_servers": null, 
        "_context_instance_lock_checked": false, 
        "_context_is_admin": true, 
        "_context_project_id": "[[[[tenant_id]]]]", 
        "_context_project_name": "[[[[tenant_id]]]]", 
        "_context_quota_class": null, 
        "_context_read_deleted": "no", 
        "_context_remote_address": "[[[[V4_2]]]]", 
        "_context_request_id": "req-[[[[UUID_0]]]]", 
        "_context_roles": [
            "checkmate", 
            "object-store:default", 
            "compute:default", 
            "identity:user-admin", 
            "admin"
        ], 
        "_context_tenant": "[[[[tenant_id]]]]", 
        "_context_timestamp": "[[[[DT_5]]]]", 
        "_context_user": "[[[[user_id]]]]", 
        "_context_user_id": "[[[[user_id]]]]", 
        "_context_user_name": "[[[[user_id]]]]", 
        "_unique_id": "[[[[XUUID_8]]]]", 
        "event_type": "compute.instance.rebuild.start", 
        "message_id": "[[[[UUID_12]]]]", 
        "payload": {
            "access_ip_v4": "[[[[V4_0]]]]", 
            "access_ip_v6": "[[[[V6_0]]]]", 
            "architecture": "x64", 
            "availability_zone": null, 
            "created_at": "[[[[DT_1]]]]", 
            "deleted_at": "", 
            "disk_gb": 40, 
            "display_name": "[[[[display_name]]]]", 
            "ephemeral_gb": 0, 
            "host": "[[[[host]]]]", 
            "hostname": "[[[[hostname]]]]", 
            "image_meta": {
                "auto_disk_config": "True", 
                "cache_in_nova": "True", 
                "container_format": "ovf", 
                "disk_format": "vhd", 
                "image_type": "base", 
                "min_disk": "40", 
                "min_ram": "512", 
                "org.openstack__1__architecture": "x64", 
                "org.openstack__1__os_distro": "org.centos", 
                "org.openstack__1__os_version": "5.10", 
                "os_distro": "centos", 
                "os_type": "linux"
            }, 
            "image_name": "[[[[image_name]]]]", 
            "image_ref_url": "http://[[[[V4_4]]]]:9292/images/[[[[UUID_2]]]]", 
            "instance_flavor_id": "3", 
            "instance_id": "[[[[UUID_1]]]]", 
            "instance_type": "1GB Standard Instance", 
            "instance_type_id": 3, 
            "kernel_id": "", 
            "launched_at": "[[[[DT_13]]]]", 
            "memory_mb": 1024, 
            "metadata": {}, 
            "node": "[[[[node]]]]", 
            "os_type": "linux", 
            "ramdisk_id": "", 
            "reservation_id": "[[[[reservation_id]]]]", 
            "root_gb": 40, 
            "state": "active", 
            "state_description": "rebuilding", 
            "tenant_id": "[[[[tenant_id]]]]", 
            "terminated_at": "", 
            "user_id": "[[[[user_id]]]]", 
            "vcpus": 1
        }, 
        "priority": "INFO", 
        "publisher_id": "[[[[publisher_id]]]]", 
        "timestamp": "[[[[DT_16]]]]"
    }, 
    {
        "_context_auth_token": "[[[[XUUID_0]]]]", 
        "_context_glance_api_servers": null, 
        "_context_instance_lock_checked": false, 
        "_context_is_admin": false, 
        "_context_project_id": "[[[[tenant_id]]]]", 
        "_context_project_name": "[[[[tenant_id]]]]", 
        "_context_quota_class": null, 
        "_context_read_deleted": "no", 
        "_context_remote_address": "[[[[V4_2]]]]", 
        "_context_request_id": "req-[[[[UUID_0]]]]", 
        "_context_roles": [
            "checkmate", 
            "object-store:default", 
            "compute:default", 
            "identity:user-admin", 
            "admin"
        ], 
        "_context_tenant": "[[[[tenant_id]]]]", 
        "_context_timestamp": "[[[[DT_5]]]]", 
        "_context_user": "[[[[user_id]]]]", 
        "_context_user_id": "[[[[user_id]]]]", 
        "_context_user_name": "[[[[user_id]]]]", 
        "_unique_id": "[[[[XUUID_9]]]]", 
        "event_type": "compute.instance.update", 
        "message_id": "[[[[UUID_13]]]]", 
        "payload": {
            "access_ip_v4": "[[[[V4_0]]]]", 
            "access_ip_v6": "[[[[V6_0]]]]", 
            "architecture": "x64", 
            "audit_period_beginning": "[[[[DT_0]]]]", 
            "audit_period_ending": "[[[[DT_13]]]]", 
            "availability_zone": null, 
            "bandwidth": {
                "private": {
                    "bw_in": 0, 
                    "bw_out": 0
                }, 
                "public": {
                    "bw_in": 0, 
                    "bw_out": 0
                }
            }, 
            "created_at": "[[[[DT_1]]]]", 
            "deleted_at": "", 
            "disk_gb": 40, 
            "display_name": "[[[[display_name]]]]", 
            "ephemeral_gb": 0, 
            "host": "[[[[host]]]]", 
            "hostname": "[[[[hostname]]]]", 
            "image_meta": {
                "auto_disk_config": "True", 
                "cache_in_nova": "True", 
                "container_format": "ovf", 
                "disk_format": "vhd", 
                "image_type": "base", 
                "min_disk": "40", 
                "min_ram": "512", 
                "org.openstack__1__architecture": "x64", 
                "org.openstack__1__os_distro": "org.centos", 
                "org.openstack__1__os_version": "5.10", 
                "os_distro": "centos", 
                "os_type": "linux"
            }, 
            "image_ref_url": "http://[[[[V4_4]]]]:9292/images/[[[[UUID_2]]]]", 
            "instance_flavor_id": "3", 
            "instance_id": "[[[[UUID_1]]]]", 
            "instance_type": "1GB Standard Instance", 
            "instance_type_id": 3, 
            "kernel_id": "", 
            "launched_at": "[[[[DT_13]]]]", 
            "memory_mb": 1024, 
            "metadata": {}, 
            "new_task_state": "rebuilding", 
            "node": "[[[[node]]]]", 
            "old_state": null, 
            "old_task_state": null, 
            "os_type": "linux", 
            "ramdisk_id": "", 
            "reservation_id": "[[[[reservation_id]]]]", 
            "root_gb": 40, 
            "state": "active", 
            "state_description": "rebuilding", 
            "tenant_id": "[[[[tenant_id]]]]", 
            "terminated_at": "", 
            "user_id": "[[[[user_id]]]]", 
            "vcpus": 1
        }, 
        "priority": "INFO", 
        "publisher_id": "[[[[publisher_id]]]]", 
        "timestamp": "[[[[DT_17]]]]"
    }, 
    {
        "_context_auth_token": "[[[[XUUID_0]]]]", 
        "_context_glance_api_servers": null, 
        "_context_instance_lock_checked": false, 
        "_context_is_admin": false, 
        "_context_project_id": "[[[[tenant_id]]]]", 
        "_context_project_name": "[[[[tenant_id]]]]", 
        "_context_quota_class": null, 
        "_context_read_deleted": "no", 
        "_context_remote_address": "[[[[V4_2]]]]", 
        "_context_request_id": "req-[[[[UUID_0]]]]", 
        "_context_roles": [
            "checkmate", 
            "object-store:default", 
            "compute:default", 
            "identity:user-admin", 
            "admin"
        ], 
        "_context_tenant": "[[[[tenant_id]]]]", 
        "_context_timestamp": "[[[[DT_5]]]]", 
        "_context_user": "[[[[user_id]]]]", 
        "_context_user_id": "[[[[user_id]]]]", 
        "_context_user_name": "[[[[user_id]]]]", 
        "_unique_id": "[[[[XUUID_10]]]]", 
        "event_type": "compute.instance.update", 
        "message_id": "[[[[UUID_14]]]]", 
        "payload": {
            "access_ip_v4": "[[[[V4_0]]]]", 
            "access_ip_v6": "[[[[V6_0]]]]", 
            "architecture": "x64", 
            "audit_period_beginning": "[[[[DT_0]]]]", 
            "audit_period_ending": "[[[[DT_18]]]]", 
            "availability_zone": null, 
            "bandwidth": {
                "private": {
                    "bw_in": 0, 
                    "bw_out": 0
                }, 
                "public": {
                    "bw_in": 0, 
                    "bw_out": 0
                }
            }, 
            "created_at": "[[[[DT_1]]]]", 
            "deleted_at": "", 
            "disk_gb": 40, 
            "display_name": "[[[[display_name]]]]", 
            "ephemeral_gb": 0, 
            "host": "[[[[host]]]]", 
            "hostname": "[[[[hostname]]]]", 
            "image_meta": {
                "auto_disk_config": "True", 
                "cache_in_nova": "True", 
                "container_format": "ovf", 
                "disk_format": "vhd", 
                "image_type": "base", 
                "min_disk": "40", 
                "min_ram": "512", 
                "org.openstack__1__architecture": "x64", 
                "org.openstack__1__os_distro": "org.centos", 
                "org.openstack__1__os_version": "5.10", 
                "os_distro": "centos", 
                "os_type": "linux"
            }, 
            "image_ref_url": "http://[[[[V4_4]]]]:9292/images/[[[[UUID_2]]]]", 
            "instance_flavor_id": "3", 
            "instance_id": "[[[[UUID_1]]]]", 
            "instance_type": "1GB Standard Instance", 
            "instance_type_id": 3, 
            "kernel_id": "", 
            "launched_at": "[[[[DT_13]]]]", 
            "memory_mb": 1024, 
            "metadata": {}, 
            "new_task_state": "rebuild_block_device_mapping", 
            "node": "[[[[node]]]]", 
            "old_state": "active", 
            "old_task_state": "rebuilding", 
            "os_type": "linux", 
            "ramdisk_id": "", 
            "reservation_id": "[[[[reservation_id]]]]", 
            "root_gb": 40, 
            "state": "active", 
            "state_description": "rebuild_block_device_mapping", 
            "tenant_id": "[[[[tenant_id]]]]", 
            "terminated_at": "", 
            "user_id": "[[[[user_id]]]]", 
            "vcpus": 1
        }, 
        "priority": "INFO", 
        "publisher_id": "[[[[publisher_id]]]]", 
        "timestamp": "[[[[DT_19]]]]"
    }, 
    {
        "_context_auth_token": "[[[[XUUID_0]]]]", 
        "_context_glance_api_servers": null, 
        "_context_instance_lock_checked": false, 
        "_context_is_admin": false, 
        "_context_project_id": "[[[[tenant_id]]]]", 
        "_context_project_name": "[[[[tenant_id]]]]", 
        "_context_quota_class": null, 
        "_context_read_deleted": "no", 
        "_context_remote_address": "[[[[V4_2]]]]", 
        "_context_request_id": "req-[[[[UUID_0]]]]", 
        "_context_roles": [
            "checkmate", 
            "object-store:default", 
            "compute:default", 
            "identity:user-admin", 
            "admin"
        ], 
        "_context_tenant": "[[[[tenant_id]]]]", 
        "_context_timestamp": "[[[[DT_5]]]]", 
        "_context_user": "[[[[user_id]]]]", 
        "_context_user_id": "[[[[user_id]]]]", 
        "_context_user_name": "[[[[user_id]]]]", 
        "_unique_id": "[[[[XUUID_11]]]]", 
        "event_type": "compute.instance.update", 
        "message_id": "[[[[UUID_15]]]]", 
        "payload": {
            "access_ip_v4": "[[[[V4_0]]]]", 
            "access_ip_v6": "[[[[V6_0]]]]", 
            "architecture": "x64", 
            "audit_period_beginning": "[[[[DT_0]]]]", 
            "audit_period_ending": "[[[[DT_18]]]]", 
            "availability_zone": null, 
            "bandwidth": {
                "private": {
                    "bw_in": 0, 
                    "bw_out": 0
                }, 
                "public": {
                    "bw_in": 0, 
                    "bw_out": 0
                }
            }, 
            "created_at": "[[[[DT_1]]]]", 
            "deleted_at": "", 
            "disk_gb": 40, 
            "display_name": "[[[[display_name]]]]", 
            "ephemeral_gb": 0, 
            "host": "[[[[host]]]]", 
            "hostname": "[[[[hostname]]]]", 
            "image_meta": {
                "auto_disk_config": "True", 
                "cache_in_nova": "True", 
                "container_format": "ovf", 
                "disk_format": "vhd", 
                "image_type": "base", 
                "min_disk": "40", 
                "min_ram": "512", 
                "org.openstack__1__architecture": "x64", 
                "org.openstack__1__os_distro": "org.centos", 
                "org.openstack__1__os_version": "5.10", 
                "os_distro": "centos", 
                "os_type": "linux"
            }, 
            "image_ref_url": "http://[[[[V4_4]]]]:9292/images/[[[[UUID_2]]]]", 
            "instance_flavor_id": "3", 
            "instance_id": "[[[[UUID_1]]]]", 
            "instance_type": "1GB Standard Instance", 
            "instance_type_id": 3, 
            "kernel_id": "", 
            "launched_at": "[[[[DT_13]]]]", 
            "memory_mb": 1024, 
            "metadata": {}, 
            "new_task_state": "rebuild_spawning", 
            "node": "[[[[node]]]]", 
            "old_state": "active", 
            "old_task_state": "rebuild_block_device_mapping", 
            "os_type": "linux", 
            "ramdisk_id": "", 
            "reservation_id": "[[[[reservation_id]]]]", 
            "root_gb": 40, 
            "state": "active", 
            "state_description": "rebuild_spawning", 
            "tenant_id": "[[[[tenant_id]]]]", 
            "terminated_at": "", 
            "user_id": "[[[[user_id]]]]", 
            "vcpus": 1
        }, 
        "priority": "INFO", 
        "publisher_id": "[[[[publisher_id]]]]", 
        "timestamp": "[[[[DT_20]]]]"
    }, 
    {
        "_context_auth_token": "[[[[XUUID_0]]]]", 
        "_context_glance_api_servers": null, 
        "_context_instance_lock_checked": false, 
        "_context_is_admin": true, 
        "_context_project_id": "[[[[tenant_id]]]]", 
        "_context_project_name": "[[[[tenant_id]]]]", 
        "_context_quota_class": null, 
        "_context_read_deleted": "no", 
        "_context_remote_address": "[[[[V4_2]]]]", 
        "_context_request_id": "req-[[[[UUID_0]]]]", 
        "_context_roles": [
            "checkmate", 
            "object-store:default", 
            "compute:default", 
            "identity:user-admin", 
            "admin"
        ], 
        "_context_tenant": "[[[[tenant_id]]]]", 
        "_context_timestamp": "[[[[DT_5]]]]", 
        "_context_user": "[[[[user_id]]]]", 
        "_context_user_id": "[[[[user_id]]]]", 
        "_context_user_name": "[[[[user_id]]]]", 
        "_unique_id": "[[[[XUUID_12]]]]", 
        "event_type": "compute.instance.update", 
        "message_id": "[[[[UUID_16]]]]", 
        "payload": {
            "access_ip_v4": "[[[[V4_0]]]]", 
            "access_ip_v6": "[[[[V6_0]]]]", 
            "architecture": "x64", 
            "audit_period_beginning": "[[[[DT_0]]]]", 
            "audit_period_ending": "[[[[DT_21]]]]", 
            "availability_zone": null, 
            "bandwidth": {
                "private": {
                    "bw_in": 0, 
                    "bw_out": 0
                }, 
                "public": {
                    "bw_in": 0, 
                    "bw_out": 0
                }
            }, 
            "created_at": "[[[[DT_1]]]]", 
            "deleted_at": "", 
            "disk_gb": 40, 
            "display_name": "[[[[display_name]]]]", 
            "ephemeral_gb": 0, 
            "host": "[[[[host]]]]", 
            "hostname": "[[[[hostname]]]]", 
            "image_meta": {
                "auto_disk_config": "True", 
                "cache_in_nova": "True", 
                "container_format": "ovf", 
                "disk_format": "vhd", 
                "image_type": "base", 
                "min_disk": "40", 
                "min_ram": "512", 
                "org.openstack__1__architecture": "x64", 
                "org.openstack__1__os_distro": "org.centos", 
                "org.openstack__1__os_version": "5.10", 
                "os_distro": "centos", 
                "os_type": "linux"
            }, 
            "image_ref_url": "http://[[[[V4_4]]]]:9292/images/[[[[UUID_2]]]]", 
            "instance_flavor_id": "3", 
            "instance_id": "[[[[UUID_1]]]]", 
            "instance_type": "1GB Standard Instance", 
            "instance_type_id": 3, 
            "kernel_id": "", 
            "launched_at": "[[[[DT_13]]]]", 
            "memory_mb": 1024, 
            "metadata": {}, 
            "new_task_state": "rebuild_spawning", 
            "node": "[[[[node]]]]", 
            "old_state": null, 
            "old_task_state": null, 
            "os_type": "linux", 
            "ramdisk_id": "", 
            "reservation_id": "[[[[reservation_id]]]]", 
            "root_gb": 40, 
            "state": "active", 
            "state_description": "rebuild_spawning", 
            "tenant_id": "[[[[tenant_id]]]]", 
            "terminated_at": "", 
            "user_id": "[[[[user_id]]]]", 
            "vcpus": 1
        }, 
        "priority": "INFO", 
        "publisher_id": "[[[[publisher_id]]]]", 
        "timestamp": "[[[[DT_22]]]]"
    }, 
    {
        "_context_auth_token": "[[[[XUUID_0]]]]", 
        "_context_glance_api_servers": null, 
        "_context_instance_lock_checked": false, 
        "_context_is_admin": true, 
        "_context_project_id": "[[[[tenant_id]]]]", 
        "_context_project_name": "[[[[tenant_id]]]]", 
        "_context_quota_class": null, 
        "_context_read_deleted": "no", 
        "_context_remote_address": "[[[[V4_2]]]]", 
        "_context_request_id": "req-[[[[UUID_0]]]]", 
        "_context_roles": [
            "checkmate", 
            "object-store:default", 
            "compute:default", 
            "identity:user-admin", 
            "admin"
        ], 
        "_context_tenant": "[[[[tenant_id]]]]", 
        "_context_timestamp": "[[[[DT_5]]]]", 
        "_context_user": "[[[[user_id]]]]", 
        "_context_user_id": "[[[[user_id]]]]", 
        "_context_user_name": "[[[[user_id]]]]", 
        "_unique_id": "[[[[XUUID_13]]]]", 
        "event_type": "compute.instance.update", 
        "message_id": "[[[[UUID_17]]]]", 
        "payload": {
            "access_ip_v4": "[[[[V4_0]]]]", 
            "access_ip_v6": "[[[[V6_0]]]]", 
            "architecture": "x64", 
            "audit_period_beginning": "[[[[DT_0]]]]", 
            "audit_period_ending": "[[[[DT_23]]]]", 
            "availability_zone": null, 
            "bandwidth": {
                "private": {
                    "bw_in": 0, 
                    "bw_out": 0
                }, 
                "public": {
                    "bw_in": 0, 
                    "bw_out": 0
                }
            }, 
            "created_at": "[[[[DT_1]]]]", 
            "deleted_at": "", 
            "disk_gb": 40, 
            "display_name": "[[[[display_name]]]]", 
            "ephemeral_gb": 0, 
            "host": "[[[[host]]]]", 
            "hostname": "[[[[hostname]]]]", 
            "image_meta": {
                "auto_disk_config": "True", 
                "cache_in_nova": "True", 
                "container_format": "ovf", 
                "disk_format": "vhd", 
                "image_type": "base", 
                "min_disk": "40", 
                "min_ram": "512", 
                "org.openstack__1__architecture": "x64", 
                "org.openstack__1__os_distro": "org.centos", 
                "org.openstack__1__os_version": "5.10", 
                "os_distro": "centos", 
                "os_type": "linux"
            }, 
            "image_ref_url": "http://[[[[V4_4]]]]:9292/images/[[[[UUID_2]]]]", 
            "instance_flavor_id": "3", 
            "instance_id": "[[[[UUID_1]]]]", 
            "instance_type": "1GB Standard Instance", 
            "instance_type_id": 3, 
            "kernel_id": "", 
            "launched_at": "[[[[DT_13]]]]", 
            "memory_mb": 1024, 
            "metadata": {}, 
            "new_task_state": "rebuild_spawning", 
            "node": "[[[[node]]]]", 
            "old_state": null, 
            "old_task_state": null, 
            "os_type": "linux", 
            "ramdisk_id": "", 
            "reservation_id": "[[[[reservation_id]]]]", 
            "root_gb": 40, 
            "state": "active", 
            "state_description": "rebuild_spawning", 
            "tenant_id": "[[[[tenant_id]]]]", 
            "terminated_at": "", 
            "user_id": "[[[[user_id]]]]", 
            "vcpus": 1
        }, 
        "priority": "INFO", 
        "publisher_id": "[[[[publisher_id]]]]", 
        "timestamp": "[[[[DT_24]]]]"
    }, 
    {
        "_context_auth_token": "[[[[XUUID_0]]]]", 
        "_context_glance_api_servers": null, 
        "_context_instance_lock_checked": false, 
        "_context_is_admin": true, 
        "_context_project_id": "[[[[tenant_id]]]]", 
        "_context_project_name": "[[[[tenant_id]]]]", 
        "_context_quota_class": null, 
        "_context_read_deleted": "no", 
        "_context_remote_address": "[[[[V4_2]]]]", 
        "_context_request_id": "req-[[[[UUID_0]]]]", 
        "_context_roles": [
            "checkmate", 
            "object-store:default", 
            "compute:default", 
            "identity:user-admin", 
            "admin"
        ], 
        "_context_tenant": "[[[[tenant_id]]]]", 
        "_context_timestamp": "[[[[DT_5]]]]", 
        "_context_user": "[[[[user_id]]]]", 
        "_context_user_id": "[[[[user_id]]]]", 
        "_context_user_name": "[[[[user_id]]]]", 
        "_unique_id": "[[[[XUUID_14]]]]", 
        "event_type": "compute.instance.update", 
        "message_id": "[[[[UUID_18]]]]", 
        "payload": {
            "access_ip_v4": "[[[[V4_0]]]]", 
            "access_ip_v6": "[[[[V6_0]]]]", 
            "architecture": "x64", 
            "audit_period_beginning": "[[[[DT_0]]]]", 
            "audit_period_ending": "[[[[DT_23]]]]", 
            "availability_zone": null, 
            "bandwidth": {
                "private": {
                    "bw_in": 0, 
                    "bw_out": 0
                }, 
                "public": {
                    "bw_in": 0, 
                    "bw_out": 0
                }
            }, 
            "created_at": "[[[[DT_1]]]]", 
            "deleted_at": "", 
            "disk_gb": 40, 
            "display_name": "[[[[display_name]]]]", 
            "ephemeral_gb": 0, 
            "host": "[[[[host]]]]", 
            "hostname": "[[[[hostname]]]]", 
            "image_meta": {
                "auto_disk_config": "True", 
                "cache_in_nova": "True", 
                "container_format": "ovf", 
                "disk_format": "vhd", 
                "image_type": "base", 
                "min_disk": "40", 
                "min_ram": "512", 
                "org.openstack__1__architecture": "x64", 
                "org.openstack__1__os_distro": "org.centos", 
                "org.openstack__1__os_version": "5.10", 
                "os_distro": "centos", 
                "os_type": "linux"
            }, 
            "image_ref_url": "http://[[[[V4_4]]]]:9292/images/[[[[UUID_2]]]]", 
            "instance_flavor_id": "3", 
            "instance_id": "[[[[UUID_1]]]]", 
            "instance_type": "1GB Standard Instance", 
            "instance_type_id": 3, 
            "kernel_id": "", 
            "launched_at": "[[[[DT_13]]]]", 
            "memory_mb": 1024, 
            "metadata": {}, 
            "new_task_state": "rebuild_spawning", 
            "node": "[[[[node]]]]", 
            "old_state": null, 
            "old_task_state": null, 
            "os_type": "linux", 
            "ramdisk_id": "", 
            "reservation_id": "[[[[reservation_id]]]]", 
            "root_gb": 40, 
            "state": "active", 
            "state_description": "rebuild_spawning", 
            "tenant_id": "[[[[tenant_id]]]]", 
            "terminated_at": "", 
            "user_id": "[[[[user_id]]]]", 
            "vcpus": 1
        }, 
        "priority": "INFO", 
        "publisher_id": "[[[[publisher_id]]]]", 
        "timestamp": "[[[[DT_25]]]]"
    }, 
    {
        "_context_auth_token": "[[[[XUUID_0]]]]", 
        "_context_glance_api_servers": null, 
        "_context_instance_lock_checked": false, 
        "_context_is_admin": true, 
        "_context_project_id": "[[[[tenant_id]]]]", 
        "_context_project_name": "[[[[tenant_id]]]]", 
        "_context_quota_class": null, 
        "_context_read_deleted": "no", 
        "_context_remote_address": "[[[[V4_2]]]]", 
        "_context_request_id": "req-[[[[UUID_0]]]]", 
        "_context_roles": [
            "checkmate", 
            "object-store:default", 
            "compute:default", 
            "identity:user-admin", 
            "admin"
        ], 
        "_context_tenant": "[[[[tenant_id]]]]", 
        "_context_timestamp": "[[[[DT_5]]]]", 
        "_context_user": "[[[[user_id]]]]", 
        "_context_user_id": "[[[[user_id]]]]", 
        "_context_user_name": "[[[[user_id]]]]", 
        "_unique_id": "[[[[XUUID_15]]]]", 
        "event_type": "compute.instance.update", 
        "message_id": "[[[[UUID_19]]]]", 
        "payload": {
            "access_ip_v4": "[[[[V4_0]]]]", 
            "access_ip_v6": "[[[[V6_0]]]]", 
            "architecture": "x64", 
            "audit_period_beginning": "[[[[DT_0]]]]", 
            "audit_period_ending": "[[[[DT_23]]]]", 
            "availability_zone": null, 
            "bandwidth": {
                "private": {
                    "bw_in": 0, 
                    "bw_out": 0
                }, 
                "public": {
                    "bw_in": 0, 
                    "bw_out": 0
                }
            }, 
            "created_at": "[[[[DT_1]]]]", 
            "deleted_at": "", 
            "disk_gb": 40, 
            "display_name": "[[[[display_name]]]]", 
            "ephemeral_gb": 0, 
            "host": "[[[[host]]]]", 
            "hostname": "[[[[hostname]]]]", 
            "image_meta": {
                "auto_disk_config": "True", 
                "cache_in_nova": "True", 
                "container_format": "ovf", 
                "disk_format": "vhd", 
                "image_type": "base", 
                "min_disk": "40", 
                "min_ram": "512", 
                "org.openstack__1__architecture": "x64", 
                "org.openstack__1__os_distro": "org.centos", 
                "org.openstack__1__os_version": "5.10", 
                "os_distro": "centos", 
                "os_type": "linux"
            }, 
            "image_ref_url": "http://[[[[V4_4]]]]:9292/images/[[[[UUID_2]]]]", 
            "instance_flavor_id": "3", 
            "instance_id": "[[[[UUID_1]]]]", 
            "instance_type": "1GB Standard Instance", 
            "instance_type_id": 3, 
            "kernel_id": "", 
            "launched_at": "[[[[DT_13]]]]", 
            "memory_mb": 1024, 
            "metadata": {}, 
            "new_task_state": "rebuild_spawning", 
            "node": "[[[[node]]]]", 
            "old_state": null, 
            "old_task_state": null, 
            "os_type": "linux", 
            "ramdisk_id": "", 
            "reservation_id": "[[[[reservation_id]]]]", 
            "root_gb": 40, 
            "state": "active", 
            "state_description": "rebuild_spawning", 
            "tenant_id": "[[[[tenant_id]]]]", 
            "terminated_at": "", 
            "user_id": "[[[[user_id]]]]", 
            "vcpus": 1
        }, 
        "priority": "INFO", 
        "publisher_id": "[[[[publisher_id]]]]", 
        "timestamp": "[[[[DT_26]]]]"
    }, 
    {
        "_context_auth_token": "[[[[XUUID_0]]]]", 
        "_context_glance_api_servers": null, 
        "_context_instance_lock_checked": false, 
        "_context_is_admin": true, 
        "_context_project_id": "[[[[tenant_id]]]]", 
        "_context_project_name": "[[[[tenant_id]]]]", 
        "_context_quota_class": null, 
        "_context_read_deleted": "no", 
        "_context_remote_address": "[[[[V4_2]]]]", 
        "_context_request_id": "req-[[[[UUID_0]]]]", 
        "_context_roles": [
            "checkmate", 
            "object-store:default", 
            "compute:default", 
            "identity:user-admin", 
            "admin"
        ], 
        "_context_tenant": "[[[[tenant_id]]]]", 
        "_context_timestamp": "[[[[DT_5]]]]", 
        "_context_user": "[[[[user_id]]]]", 
        "_context_user_id": "[[[[user_id]]]]", 
        "_context_user_name": "[[[[user_id]]]]", 
        "_unique_id": "[[[[XUUID_16]]]]", 
        "event_type": "compute.instance.update", 
        "message_id": "[[[[UUID_20]]]]", 
        "payload": {
            "access_ip_v4": "[[[[V4_0]]]]", 
            "access_ip_v6": "[[[[V6_0]]]]", 
            "architecture": "x64", 
            "audit_period_beginning": "[[[[DT_0]]]]", 
            "audit_period_ending": "[[[[DT_27]]]]", 
            "availability_zone": null, 
            "bandwidth": {
                "private": {
                    "bw_in": 0, 
                    "bw_out": 0
                }, 
                "public": {
                    "bw_in": 0, 
                    "bw_out": 0
                }
            }, 
            "created_at": "[[[[DT_1]]]]", 
            "deleted_at": "", 
            "disk_gb": 40, 
            "display_name": "[[[[display_name]]]]", 
            "ephemeral_gb": 0, 
            "host": "[[[[host]]]]", 
            "hostname": "[[[[hostname]]]]", 
            "image_meta": {
                "auto_disk_config": "True", 
                "cache_in_nova": "True", 
                "container_format": "ovf", 
                "disk_format": "vhd", 
                "image_type": "base", 
                "min_disk": "40", 
                "min_ram": "512", 
                "org.openstack__1__architecture": "x64", 
                "org.openstack__1__os_distro": "org.centos", 
                "org.openstack__1__os_version": "5.10", 
                "os_distro": "centos", 
                "os_type": "linux"
            }, 
            "image_ref_url": "http://[[[[V4_4]]]]:9292/images/[[[[UUID_2]]]]", 
            "instance_flavor_id": "3", 
            "instance_id": "[[[[UUID_1]]]]", 
            "instance_type": "1GB Standard Instance", 
            "instance_type_id": 3, 
            "kernel_id": "", 
            "launched_at": "[[[[DT_13]]]]", 
            "memory_mb": 1024, 
            "metadata": {}, 
            "new_task_state": "rebuild_spawning", 
            "node": "[[[[node]]]]", 
            "old_state": null, 
            "old_task_state": null, 
            "os_type": "linux", 
            "ramdisk_id": "", 
            "reservation_id": "[[[[reservation_id]]]]", 
            "root_gb": 40, 
            "state": "active", 
            "state_description": "rebuild_spawning", 
            "tenant_id": "[[[[tenant_id]]]]", 
            "terminated_at": "", 
            "user_id": "[[[[user_id]]]]", 
            "vcpus": 1
        }, 
        "priority": "INFO", 
        "publisher_id": "[[[[publisher_id]]]]", 
        "timestamp": "[[[[DT_28]]]]"
    }, 
    {
        "_context_auth_token": "[[[[XUUID_0]]]]", 
        "_context_glance_api_servers": null, 
        "_context_instance_lock_checked": false, 
        "_context_is_admin": true, 
        "_context_project_id": "[[[[tenant_id]]]]", 
        "_context_project_name": "[[[[tenant_id]]]]", 
        "_context_quota_class": null, 
        "_context_read_deleted": "no", 
        "_context_remote_address": "[[[[V4_2]]]]", 
        "_context_request_id": "req-[[[[UUID_0]]]]", 
        "_context_roles": [
            "checkmate", 
            "object-store:default", 
            "compute:default", 
            "identity:user-admin", 
            "admin"
        ], 
        "_context_tenant": "[[[[tenant_id]]]]", 
        "_context_timestamp": "[[[[DT_5]]]]", 
        "_context_user": "[[[[user_id]]]]", 
        "_context_user_id": "[[[[user_id]]]]", 
        "_context_user_name": "[[[[user_id]]]]", 
        "_unique_id": "[[[[XUUID_17]]]]", 
        "event_type": "compute.instance.update", 
        "message_id": "[[[[UUID_21]]]]", 
        "payload": {
            "access_ip_v4": "[[[[V4_0]]]]", 
            "access_ip_v6": "[[[[V6_0]]]]", 
            "architecture": "x64", 
            "audit_period_beginning": "[[[[DT_0]]]]", 
            "audit_period_ending": "[[[[DT_29]]]]", 
            "availability_zone": null, 
            "bandwidth": {
                "private": {
                    "bw_in": 0, 
                    "bw_out": 0
                }, 
                "public": {
                    "bw_in": 0, 
                    "bw_out": 0
                }
            }, 
            "created_at": "[[[[DT_1]]]]", 
            "deleted_at": "", 
            "disk_gb": 40, 
            "display_name": "[[[[display_name]]]]", 
            "ephemeral_gb": 0, 
            "host": "[[[[host]]]]", 
            "hostname": "[[[[hostname]]]]", 
            "image_meta": {
                "auto_disk_config": "True", 
                "cache_in_nova": "True", 
                "container_format": "ovf", 
                "disk_format": "vhd", 
                "image_type": "base", 
                "min_disk": "40", 
                "min_ram": "512", 
                "org.openstack__1__architecture": "x64", 
                "org.openstack__1__os_distro": "org.centos", 
                "org.openstack__1__os_version": "5.10", 
                "os_distro": "centos", 
                "os_type": "linux"
            }, 
            "image_ref_url": "http://[[[[V4_4]]]]:9292/images/[[[[UUID_2]]]]", 
            "instance_flavor_id": "3", 
            "instance_id": "[[[[UUID_1]]]]", 
            "instance_type": "1GB Standard Instance", 
            "instance_type_id": 3, 
            "kernel_id": "", 
            "launched_at": "[[[[DT_13]]]]", 
            "memory_mb": 1024, 
            "metadata": {}, 
            "new_task_state": "rebuild_spawning", 
            "node": "[[[[node]]]]", 
            "old_state": null, 
            "old_task_state": null, 
            "os_type": "linux", 
            "ramdisk_id": "", 
            "reservation_id": "[[[[reservation_id]]]]", 
            "root_gb": 40, 
            "state": "active", 
            "state_description": "rebuild_spawning", 
            "tenant_id": "[[[[tenant_id]]]]", 
            "terminated_at": "", 
            "user_id": "[[[[user_id]]]]", 
            "vcpus": 1
        }, 
        "priority": "INFO", 
        "publisher_id": "[[[[publisher_id]]]]", 
        "timestamp": "[[[[DT_30]]]]"
    }, 
    {
        "_context_auth_token": "[[[[XUUID_0]]]]", 
        "_context_glance_api_servers": null, 
        "_context_instance_lock_checked": false, 
        "_context_is_admin": true, 
        "_context_project_id": "[[[[tenant_id]]]]", 
        "_context_project_name": "[[[[tenant_id]]]]", 
        "_context_quota_class": null, 
        "_context_read_deleted": "no", 
        "_context_remote_address": "[[[[V4_2]]]]", 
        "_context_request_id": "req-[[[[UUID_0]]]]", 
        "_context_roles": [
            "checkmate", 
            "object-store:default", 
            "compute:default", 
            "identity:user-admin", 
            "admin"
        ], 
        "_context_tenant": "[[[[tenant_id]]]]", 
        "_context_timestamp": "[[[[DT_5]]]]", 
        "_context_user": "[[[[user_id]]]]", 
        "_context_user_id": "[[[[user_id]]]]", 
        "_context_user_name": "[[[[user_id]]]]", 
        "_unique_id": "[[[[XUUID_18]]]]", 
        "event_type": "compute.instance.update", 
        "message_id": "[[[[UUID_22]]]]", 
        "payload": {
            "access_ip_v4": "[[[[V4_0]]]]", 
            "access_ip_v6": "[[[[V6_0]]]]", 
            "architecture": "x64", 
            "audit_period_beginning": "[[[[DT_0]]]]", 
            "audit_period_ending": "[[[[DT_31]]]]", 
            "availability_zone": null, 
            "bandwidth": {
                "private": {
                    "bw_in": 0, 
                    "bw_out": 0
                }, 
                "public": {
                    "bw_in": 0, 
                    "bw_out": 0
                }
            }, 
            "created_at": "[[[[DT_1]]]]", 
            "deleted_at": "", 
            "disk_gb": 40, 
            "display_name": "[[[[display_name]]]]", 
            "ephemeral_gb": 0, 
            "host": "[[[[host]]]]", 
            "hostname": "[[[[hostname]]]]", 
            "image_meta": {
                "auto_disk_config": "True", 
                "cache_in_nova": "True", 
                "container_format": "ovf", 
                "disk_format": "vhd", 
                "image_type": "base", 
                "min_disk": "40", 
                "min_ram": "512", 
                "org.openstack__1__architecture": "x64", 
                "org.openstack__1__os_distro": "org.centos", 
                "org.openstack__1__os_version": "5.10", 
                "os_distro": "centos", 
                "os_type": "linux"
            }, 
            "image_ref_url": "http://[[[[V4_4]]]]:9292/images/[[[[UUID_2]]]]", 
            "instance_flavor_id": "3", 
            "instance_id": "[[[[UUID_1]]]]", 
            "instance_type": "1GB Standard Instance", 
            "instance_type_id": 3, 
            "kernel_id": "", 
            "launched_at": "[[[[DT_13]]]]", 
            "memory_mb": 1024, 
            "metadata": {}, 
            "new_task_state": "rebuild_spawning", 
            "node": "[[[[node]]]]", 
            "old_state": null, 
            "old_task_state": null, 
            "os_type": "linux", 
            "ramdisk_id": "", 
            "reservation_id": "[[[[reservation_id]]]]", 
            "root_gb": 40, 
            "state": "active", 
            "state_description": "rebuild_spawning", 
            "tenant_id": "[[[[tenant_id]]]]", 
            "terminated_at": "", 
            "user_id": "[[[[user_id]]]]", 
            "vcpus": 1
        }, 
        "priority": "INFO", 
        "publisher_id": "[[[[publisher_id]]]]", 
        "timestamp": "[[[[DT_32]]]]"
    }, 
    {
        "_context_auth_token": "[[[[XUUID_0]]]]", 
        "_context_glance_api_servers": null, 
        "_context_instance_lock_checked": false, 
        "_context_is_admin": true, 
        "_context_project_id": "[[[[tenant_id]]]]", 
        "_context_project_name": "[[[[tenant_id]]]]", 
        "_context_quota_class": null, 
        "_context_read_deleted": "no", 
        "_context_remote_address": "[[[[V4_2]]]]", 
        "_context_request_id": "req-[[[[UUID_0]]]]", 
        "_context_roles": [
            "checkmate", 
            "object-store:default", 
            "compute:default", 
            "identity:user-admin", 
            "admin"
        ], 
        "_context_tenant": "[[[[tenant_id]]]]", 
        "_context_timestamp": "[[[[DT_5]]]]", 
        "_context_user": "[[[[user_id]]]]", 
        "_context_user_id": "[[[[user_id]]]]", 
        "_context_user_name": "[[[[user_id]]]]", 
        "_unique_id": "[[[[XUUID_19]]]]", 
        "event_type": "compute.instance.update", 
        "message_id": "[[[[UUID_23]]]]", 
        "payload": {
            "access_ip_v4": "[[[[V4_0]]]]", 
            "access_ip_v6": "[[[[V6_0]]]]", 
            "architecture": "x64", 
            "audit_period_beginning": "[[[[DT_0]]]]", 
            "audit_period_ending": "[[[[DT_33]]]]", 
            "availability_zone": null, 
            "bandwidth": {
                "private": {
                    "bw_in": 0, 
                    "bw_out": 0
                }, 
                "public": {
                    "bw_in": 0, 
                    "bw_out": 0
                }
            }, 
            "created_at": "[[[[DT_1]]]]", 
            "deleted_at": "", 
            "disk_gb": 40, 
            "display_name": "[[[[display_name]]]]", 
            "ephemeral_gb": 0, 
            "host": "[[[[host]]]]", 
            "hostname": "[[[[hostname]]]]", 
            "image_meta": {
                "auto_disk_config": "True", 
                "cache_in_nova": "True", 
                "container_format": "ovf", 
                "disk_format": "vhd", 
                "image_type": "base", 
                "min_disk": "40", 
                "min_ram": "512", 
                "org.openstack__1__architecture": "x64", 
                "org.openstack__1__os_distro": "org.centos", 
                "org.openstack__1__os_version": "5.10", 
                "os_distro": "centos", 
                "os_type": "linux"
            }, 
            "image_ref_url": "http://[[[[V4_4]]]]:9292/images/[[[[UUID_2]]]]", 
            "instance_flavor_id": "3", 
            "instance_id": "[[[[UUID_1]]]]", 
            "instance_type": "1GB Standard Instance", 
            "instance_type_id": 3, 
            "kernel_id": "", 
            "launched_at": "[[[[DT_13]]]]", 
            "memory_mb": 1024, 
            "metadata": {}, 
            "new_task_state": "rebuild_spawning", 
            "node": "[[[[node]]]]", 
            "old_state": null, 
            "old_task_state": null, 
            "os_type": "linux", 
            "ramdisk_id": "", 
            "reservation_id": "[[[[reservation_id]]]]", 
            "root_gb": 40, 
            "state": "active", 
            "state_description": "rebuild_spawning", 
            "tenant_id": "[[[[tenant_id]]]]", 
            "terminated_at": "", 
            "user_id": "[[[[user_id]]]]", 
            "vcpus": 1
        }, 
        "priority": "INFO", 
        "publisher_id": "[[[[publisher_id]]]]", 
        "timestamp": "[[[[DT_34]]]]"
    }, 
    {
        "_context_auth_token": "[[[[XUUID_0]]]]", 
        "_context_glance_api_servers": null, 
        "_context_instance_lock_checked": false, 
        "_context_is_admin": true, 
        "_context_project_id": "[[[[tenant_id]]]]", 
        "_context_project_name": "[[[[tenant_id]]]]", 
        "_context_quota_class": null, 
        "_context_read_deleted": "no", 
        "_context_remote_address": "[[[[V4_2]]]]", 
        "_context_request_id": "req-[[[[UUID_0]]]]", 
        "_context_roles": [
            "checkmate", 
            "object-store:default", 
            "compute:default", 
            "identity:user-admin", 
            "admin"
        ], 
        "_context_tenant": "[[[[tenant_id]]]]", 
        "_context_timestamp": "[[[[DT_5]]]]", 
        "_context_user": "[[[[user_id]]]]", 
        "_context_user_id": "[[[[user_id]]]]", 
        "_context_user_name": "[[[[user_id]]]]", 
        "_unique_id": "[[[[XUUID_20]]]]", 
        "event_type": "compute.instance.update", 
        "message_id": "[[[[UUID_24]]]]", 
        "payload": {
            "access_ip_v4": "[[[[V4_0]]]]", 
            "access_ip_v6": "[[[[V6_0]]]]", 
            "architecture": "x64", 
            "audit_period_beginning": "[[[[DT_0]]]]", 
            "audit_period_ending": "[[[[DT_35]]]]", 
            "availability_zone": null, 
            "bandwidth": {
                "private": {
                    "bw_in": 0, 
                    "bw_out": 0
                }, 
                "public": {
                    "bw_in": 0, 
                    "bw_out": 0
                }
            }, 
            "created_at": "[[[[DT_1]]]]", 
            "deleted_at": "", 
            "disk_gb": 40, 
            "display_name": "[[[[display_name]]]]", 
            "ephemeral_gb": 0, 
            "host": "[[[[host]]]]", 
            "hostname": "[[[[hostname]]]]", 
            "image_meta": {
                "auto_disk_config": "True", 
                "cache_in_nova": "True", 
                "container_format": "ovf", 
                "disk_format": "vhd", 
                "image_type": "base", 
                "min_disk": "40", 
                "min_ram": "512", 
                "org.openstack__1__architecture": "x64", 
                "org.openstack__1__os_distro": "org.centos", 
                "org.openstack__1__os_version": "5.10", 
                "os_distro": "centos", 
                "os_type": "linux"
            }, 
            "image_ref_url": "http://[[[[V4_4]]]]:9292/images/[[[[UUID_2]]]]", 
            "instance_flavor_id": "3", 
            "instance_id": "[[[[UUID_1]]]]", 
            "instance_type": "1GB Standard Instance", 
            "instance_type_id": 3, 
            "kernel_id": "", 
            "launched_at": "[[[[DT_13]]]]", 
            "memory_mb": 1024, 
            "metadata": {}, 
            "new_task_state": "rebuild_spawning", 
            "node": "[[[[node]]]]", 
            "old_state": null, 
            "old_task_state": null, 
            "os_type": "linux", 
            "ramdisk_id": "", 
            "reservation_id": "[[[[reservation_id]]]]", 
            "root_gb": 40, 
            "state": "active", 
            "state_description": "rebuild_spawning", 
            "tenant_id": "[[[[tenant_id]]]]", 
            "terminated_at": "", 
            "user_id": "[[[[user_id]]]]", 
            "vcpus": 1
        }, 
        "priority": "INFO", 
        "publisher_id": "[[[[publisher_id]]]]", 
        "timestamp": "[[[[DT_36]]]]"
    }, 
    {
        "_context_auth_token": "[[[[XUUID_0]]]]", 
        "_context_glance_api_servers": null, 
        "_context_instance_lock_checked": false, 
        "_context_is_admin": true, 
        "_context_project_id": "[[[[tenant_id]]]]", 
        "_context_project_name": "[[[[tenant_id]]]]", 
        "_context_quota_class": null, 
        "_context_read_deleted": "no", 
        "_context_remote_address": "[[[[V4_2]]]]", 
        "_context_request_id": "req-[[[[UUID_0]]]]", 
        "_context_roles": [
            "checkmate", 
            "object-store:default", 
            "compute:default", 
            "identity:user-admin", 
            "admin"
        ], 
        "_context_tenant": "[[[[tenant_id]]]]", 
        "_context_timestamp": "[[[[DT_5]]]]", 
        "_context_user": "[[[[user_id]]]]", 
        "_context_user_id": "[[[[user_id]]]]", 
        "_context_user_name": "[[[[user_id]]]]", 
        "_unique_id": "[[[[XUUID_21]]]]", 
        "event_type": "compute.instance.update", 
        "message_id": "[[[[UUID_25]]]]", 
        "payload": {
            "access_ip_v4": "[[[[V4_0]]]]", 
            "access_ip_v6": "[[[[V6_0]]]]", 
            "architecture": "x64", 
            "audit_period_beginning": "[[[[DT_0]]]]", 
            "audit_period_ending": "[[[[DT_35]]]]", 
            "availability_zone": null, 
            "bandwidth": {
                "private": {
                    "bw_in": 0, 
                    "bw_out": 0
                }, 
                "public": {
                    "bw_in": 0, 
                    "bw_out": 0
                }
            }, 
            "created_at": "[[[[DT_1]]]]", 
            "deleted_at": "", 
            "disk_gb": 40, 
            "display_name": "[[[[display_name]]]]", 
            "ephemeral_gb": 0, 
            "host": "[[[[host]]]]", 
            "hostname": "[[[[hostname]]]]", 
            "image_meta": {
                "auto_disk_config": "True", 
                "cache_in_nova": "True", 
                "container_format": "ovf", 
                "disk_format": "vhd", 
                "image_type": "base", 
                "min_disk": "40", 
                "min_ram": "512", 
                "org.openstack__1__architecture": "x64", 
                "org.openstack__1__os_distro": "org.centos", 
                "org.openstack__1__os_version": "5.10", 
                "os_distro": "centos", 
                "os_type": "linux"
            }, 
            "image_ref_url": "http://[[[[V4_4]]]]:9292/images/[[[[UUID_2]]]]", 
            "instance_flavor_id": "3", 
            "instance_id": "[[[[UUID_1]]]]", 
            "instance_type": "1GB Standard Instance", 
            "instance_type_id": 3, 
            "kernel_id": "", 
            "launched_at": "[[[[DT_13]]]]", 
            "memory_mb": 1024, 
            "metadata": {}, 
            "new_task_state": "rebuild_spawning", 
            "node": "[[[[node]]]]", 
            "old_state": null, 
            "old_task_state": null, 
            "os_type": "linux", 
            "ramdisk_id": "", 
            "reservation_id": "[[[[reservation_id]]]]", 
            "root_gb": 40, 
            "state": "active", 
            "state_description": "rebuild_spawning", 
            "tenant_id": "[[[[tenant_id]]]]", 
            "terminated_at": "", 
            "user_id": "[[[[user_id]]]]", 
            "vcpus": 1
        }, 
        "priority": "INFO", 
        "publisher_id": "[[[[publisher_id]]]]", 
        "timestamp": "[[[[DT_37]]]]"
    }, 
    {
        "_context_auth_token": "[[[[XUUID_0]]]]", 
        "_context_glance_api_servers": null, 
        "_context_instance_lock_checked": false, 
        "_context_is_admin": false, 
        "_context_project_id": "[[[[tenant_id]]]]", 
        "_context_project_name": "[[[[tenant_id]]]]", 
        "_context_quota_class": null, 
        "_context_read_deleted": "no", 
        "_context_remote_address": "[[[[V4_2]]]]", 
        "_context_request_id": "req-[[[[UUID_0]]]]", 
        "_context_roles": [
            "checkmate", 
            "object-store:default", 
            "compute:default", 
            "identity:user-admin", 
            "admin"
        ], 
        "_context_tenant": "[[[[tenant_id]]]]", 
        "_context_timestamp": "[[[[DT_5]]]]", 
        "_context_user": "[[[[user_id]]]]", 
        "_context_user_id": "[[[[user_id]]]]", 
        "_context_user_name": "[[[[user_id]]]]", 
        "_unique_id": "[[[[XUUID_22]]]]", 
        "event_type": "compute.instance.update", 
        "message_id": "[[[[UUID_26]]]]", 
        "payload": {
            "access_ip_v4": "[[[[V4_0]]]]", 
            "access_ip_v6": "[[[[V6_0]]]]", 
            "architecture": "x64", 
            "audit_period_beginning": "[[[[DT_0]]]]", 
            "audit_period_ending": "[[[[DT_35]]]]", 
            "availability_zone": null, 
            "bandwidth": {
                "private": {
                    "bw_in": 0, 
                    "bw_out": 0
                }, 
                "public": {
                    "bw_in": 0, 
                    "bw_out": 0
                }
            }, 
            "created_at": "[[[[DT_1]]]]", 
            "deleted_at": "", 
            "disk_gb": 40, 
            "display_name": "[[[[display_name]]]]", 
            "ephemeral_gb": 0, 
            "host": "[[[[host]]]]", 
            "hostname": "[[[[hostname]]]]", 
            "image_meta": {
                "auto_disk_config": "True", 
                "cache_in_nova": "True", 
                "container_format": "ovf", 
                "disk_format": "vhd", 
                "image_type": "base", 
                "min_disk": "40", 
                "min_ram": "512", 
                "org.openstack__1__architecture": "x64", 
                "org.openstack__1__os_distro": "org.centos", 
                "org.openstack__1__os_version": "5.10", 
                "os_distro": "centos", 
                "os_type": "linux"
            }, 
            "image_ref_url": "http://[[[[V4_4]]]]:9292/images/[[[[UUID_2]]]]", 
            "instance_flavor_id": "3", 
            "instance_id": "[[[[UUID_1]]]]", 
            "instance_type": "1GB Standard Instance", 
            "instance_type_id": 3, 
            "kernel_id": "", 
            "launched_at": "[[[[DT_35]]]]", 
            "memory_mb": 1024, 
            "metadata": {}, 
            "new_task_state": null, 
            "node": "[[[[node]]]]", 
            "old_state": "active", 
            "old_task_state": "rebuild_spawning", 
            "os_type": "linux", 
            "ramdisk_id": "", 
            "reservation_id": "[[[[reservation_id]]]]", 
            "root_gb": 40, 
            "state": "active", 
            "state_description": "", 
            "tenant_id": "[[[[tenant_id]]]]", 
            "terminated_at": "", 
            "user_id": "[[[[user_id]]]]", 
            "vcpus": 1
        }, 
        "priority": "INFO", 
        "publisher_id": "[[[[publisher_id]]]]", 
        "timestamp": "[[[[DT_38]]]]"
    }, 
    {
        "_context_auth_token": "[[[[XUUID_0]]]]", 
        "_context_glance_api_servers": null, 
        "_context_instance_lock_checked": false, 
        "_context_is_admin": true, 
        "_context_project_id": "[[[[tenant_id]]]]", 
        "_context_project_name": "[[[[tenant_id]]]]", 
        "_context_quota_class": null, 
        "_context_read_deleted": "no", 
        "_context_remote_address": "[[[[V4_2]]]]", 
        "_context_request_id": "req-[[[[UUID_0]]]]", 
        "_context_roles": [
            "checkmate", 
            "object-store:default", 
            "compute:default", 
            "identity:user-admin", 
            "admin"
        ], 
        "_context_tenant": "[[[[tenant_id]]]]", 
        "_context_timestamp": "[[[[DT_5]]]]", 
        "_context_user": "[[[[user_id]]]]", 
        "_context_user_id": "[[[[user_id]]]]", 
        "_context_user_name": "[[[[user_id]]]]", 
        "_unique_id": "[[[[XUUID_23]]]]", 
        "event_type": "compute.instance.rebuild.end", 
        "message_id": "[[[[UUID_27]]]]", 
        "payload": {
            "access_ip_v4": "[[[[V4_0]]]]", 
            "access_ip_v6": "[[[[V6_0]]]]", 
            "architecture": "x64", 
            "availability_zone": null, 
            "created_at": "[[[[DT_1]]]]", 
            "deleted_at": "", 
            "disk_gb": 40, 
            "display_name": "[[[[display_name]]]]", 
            "ephemeral_gb": 0, 
            "fixed_ips": [
                {
                    "address": "[[[[V4_0]]]]", 
                    "floating_ips": [], 
                    "label": "public", 
                    "meta": {}, 
                    "type": "fixed", 
                    "version": 4
                }, 
                {
                    "address": "[[[[V6_0]]]]", 
                    "floating_ips": [], 
                    "label": "public", 
                    "meta": {}, 
                    "type": "fixed", 
                    "version": 6
                }, 
                {
                    "address": "[[[[V4_5]]]]", 
                    "floating_ips": [], 
                    "label": "private", 
                    "meta": {}, 
                    "type": "fixed", 
                    "version": 4
                }
            ], 
            "host": "[[[[host]]]]", 
            "hostname": "[[[[hostname]]]]", 
            "image_meta": {
                "auto_disk_config": "True", 
                "cache_in_nova": "True", 
                "container_format": "ovf", 
                "disk_format": "vhd", 
                "image_type": "base", 
                "min_disk": "40", 
                "min_ram": "512", 
                "org.openstack__1__architecture": "x64", 
                "org.openstack__1__os_distro": "org.centos", 
                "org.openstack__1__os_version": "5.10", 
                "os_distro": "centos", 
                "os_type": "linux"
            }, 
            "image_name": "[[[[image_name]]]]", 
            "image_ref_url": "http://[[[[V4_4]]]]:9292/images/[[[[UUID_2]]]]", 
            "instance_flavor_id": "3", 
            "instance_id": "[[[[UUID_1]]]]", 
            "instance_type": "1GB Standard Instance", 
            "instance_type_id": 3, 
            "kernel_id": "", 
            "launched_at": "[[[[DT_35]]]]", 
            "memory_mb": 1024, 
            "metadata": {}, 
            "node": "[[[[node]]]]", 
            "os_type": "linux", 
            "ramdisk_id": "", 
            "reservation_id": "[[[[reservation_id]]]]", 
            "root_gb": 40, 
            "state": "active", 
            "state_description": "", 
            "tenant_id": "[[[[tenant_id]]]]", 
            "terminated_at": "", 
            "user_id": "[[[[user_id]]]]", 
            "vcpus": 1
        }, 
        "priority": "INFO", 
        "publisher_id": "[[[[publisher_id]]]]", 
        "timestamp": "[[[[DT_39]]]]"
    }
]